BOWaves/__init__.py
BOWaves/bowav/__init__.py
BOWaves/bowav/bowav_feature_extractor.py
BOWaves/scripts/__init__.py
BOWaves/scripts/gen_morlet_signal.py
BOWaves/scripts/run_sikmeans.py
BOWaves/sikmeans/__init__.py
BOWaves/sikmeans/sample_data_gen.py
BOWaves/sikmeans/sikmeans_core.py
BOWaves/utilities/__init__.py
BOWaves/utilities/dataloaders.py
BOWaves/utilities/datasets.py
BOWaves/utilities/sikmeans_utils.py
BOWaves/utilities/utils.py
BOWaves/utilities/visualization.py
BOWaves/utilities/wrappers.py
BOWaves-0.0.26.dist-info/METADATA
BOWaves-0.0.26.dist-info/WHEEL
BOWaves-0.0.26.dist-info/top_level.txt
BOWaves-0.0.26.dist-info/RECORD
