Metadata-Version: 2.1
Name: BOWaves
Version: 0.0.26
Summary: Learning representative waveforms
Author: ameek2 (CNIEL @ UD)
Author-email: <austin.meek10@gmail.com>
Keywords: python,EEG,time series,dictionary learning
Classifier: Development Status :: 1 - Planning
Classifier: Intended Audience :: Developers
Classifier: Programming Language :: Python :: 3
Classifier: Operating System :: Unix
Classifier: Operating System :: MacOS :: MacOS X
Classifier: Operating System :: Microsoft :: Windows
